log4func/__init__.py
log4func/log4func.py
log4func-0.1.0.dist-info/LICENSE
log4func-0.1.0.dist-info/METADATA
log4func-0.1.0.dist-info/WHEEL
log4func-0.1.0.dist-info/top_level.txt
log4func-0.1.0.dist-info/RECORD
