Metadata-Version: 2.1
Name: log4func
Version: 0.1.0
Summary: logging helper for functions and methods
Home-page: https://github.com/bugph0bia/log4func
Author: bugph0bia
Author-email: 
License: MIT
Platform: UNKNOWN
Classifier: Topic :: System :: Logging
Classifier: Topic :: Software Development :: Libraries :: Python Modules
Classifier: Programming Language :: Python :: 3 :: Only
Classifier: License :: OSI Approved :: MIT License
Classifier: Intended Audience :: Developers
